Metadata-Version: 1.1
Name: pytest-failed-screenshot
Version: 1.0.2
Summary: Test case fails,take a screenshot,save it,attach it to the allure
Home-page: https://github.com/fungaegis/pytest-failed-screenshot
Author: fungaegis
Author-email: fungaegis@gmail.com
License: MIT License
Keywords: pytest,py.test,pytest_failed_screenshot,allure,screenshot,selenium,appium
Platform: UNKNOWN
Classifier: Framework :: Pytest
Classifier: Programming Language :: Python :: 3
Classifier: Topic :: Software Development :: Testing
Classifier: Programming Language :: Python :: 3.7
